pytc3/__init__.py
pytc3/base.py
pytc3/exceptions.py
pytc3/manager.py
pytc3/mixins.py
pytc3/objects.py
pytc3/teamcity.py
pytc3/utils.py
pytc3-0.1.1.dist-info/METADATA
pytc3-0.1.1.dist-info/RECORD
pytc3-0.1.1.dist-info/WHEEL
pytc3-0.1.1.dist-info/top_level.txt
