Metadata-Version: 2.1
Name: pytc3
Version: 0.1.1
Summary: Use the TeamCity REST API from Python
Home-page: https://github.com/ageekymonk/pytc3
Author: ageekymonk
Author-email: ramzthecoder@gmail.com
Maintainer: ageekymonk
Maintainer-email: ramzthecoder@gmail.com
License: MIT
Platform: UNKNOWN
Classifier: Programming Language :: Python :: 3.6
Classifier: Natural Language :: English
Classifier: Intended Audience :: Developers
Provides-Extra: tests
Requires-Dist: beautifulsoup4
Requires-Dist: python-dateutil
Requires-Dist: pytz
Requires-Dist: requests
Provides-Extra: tests
Requires-Dist: mock (>=2.0.0); extra == 'tests'
Requires-Dist: pytest (>=3.0.2); extra == 'tests'
Requires-Dist: pytest-cov (>=2.3.1); extra == 'tests'
Requires-Dist: responses (>=0.5.1); extra == 'tests'
